{
  "dogs": [
    {
      "name": "Alexander Rosario",
      "image": "/assets/chihuahua.avif",
      "description": "sss",
      "isFavorite": true,
      "id": 65
    },
    {
      "name": "Alex Rosario",
      "image": "/assets/blue-heeler.png",
      "description": "good",
      "isFavorite": true,
      "id": 70
    },
    {
      "name": "Money",
      "image": "/assets/blue-heeler.png",
      "description": "df",
      "isFavorite": true,
      "id": 71
    },
    {
      "name": "Inanna",
      "image": "/assets/boxer.jpeg",
      "description": "gg",
      "isFavorite": true,
      "id": 76
    },
    {
      "name": "Alex Rosario",
      "image": "/assets/chihuahua.avif",
      "description": "s",
      "isFavorite": true,
      "id": 77
    },
    {
      "name": "George C Fluffles",
      "image": "/assets/chihuahua.avif",
      "description": "Sophist",
      "isFavorite": true,
      "id": 78
    },
    {
      "name": "dd",
      "image": "/assets/blue-heeler.png",
      "description": "d",
      "isFavorite": false,
      "id": 84
    },
    {
      "name": "",
      "image": "/assets/blue-heeler.png",
      "description": "",
      "isFavorite": false,
      "id": 86
    },
    {
      "name": "s",
      "image": "/assets/blue-heeler.png",
      "description": "s",
      "isFavorite": false,
      "id": 87
    },
    {
      "name": "Money",
      "image": "/assets/blue-heeler.png",
      "description": "nn",
      "isFavorite": false,
      "id": 88
    },
    {
      "name": "Malaya",
      "image": "/assets/corgi.png",
      "description": "Barks a lot",
      "isFavorite": false,
      "id": 91
    },
    {
      "name": "s",
      "image": "/assets/boxer.jpeg",
      "description": "d",
      "isFavorite": true,
      "id": 92
    },
    {
      "name": "Money",
      "image": "/assets/dalmation.png",
      "description": "r",
      "isFavorite": false,
      "id": 93
    },
    {
      "name": "s",
      "image": "/assets/blue-heeler.png",
      "description": "s",
      "isFavorite": true,
      "id": 94
    },
    {
      "name": "s",
      "image": "/assets/boxer.jpeg",
      "description": "s",
      "isFavorite": true,
      "id": 95
    },
    {
      "name": "",
      "image": "/assets/blue-heeler.png",
      "description": "",
      "isFavorite": true,
      "id": 98
    },
    {
      "name": "s",
      "image": "/assets/blue-heeler.png",
      "description": "d",
      "isFavorite": true,
      "id": 99
    },
    {
      "name": "Pollo",
      "image": "/assets/Golden.jpeg",
      "description": "The best frigging dog ever! he's a good boy",
      "isFavorite": true,
      "id": 101
    },
    {
      "name": "Money",
      "image": "/assets/blue-heeler.png",
      "description": "g",
      "isFavorite": false,
      "id": 102
    },
    {
      "name": "wally",
      "image": "/assets/Golden.jpeg",
      "description": "Gee willy",
      "isFavorite": false,
      "id": 103
    },
    {
      "name": "Money",
      "image": "/assets/blue-heeler.png",
      "description": "man",
      "isFavorite": true,
      "id": 104
    }
  ]
}